{
  "id": 17,
  "name": "Lorraine Hansberry (1930-05-19 \u2013 1965-01-12)",
  "birth_date": "1930-05-19",
  "death_date": "1965-01-12",
  "nationality": "American",
  "bio": "Lorraine Hansberry was a groundbreaking African-American playwright and writer, best known for her play *A Raisin in the Sun*, which depicted the struggles and aspirations of a Black family in Chicago. She was the first African-American woman to have a play performed on Broadway and the youngest American playwright to win the New York Drama Critics' Circle Award.",
  "works": []
}